pythononwheels/__init__.py
pythononwheels/generate_app.py
pythononwheels/tasks.py
pythononwheels/start/LICENCE.txt
pythononwheels/start/README.md
pythononwheels/start/__init__.py
pythononwheels/start/generate_dash.py
pythononwheels/start/generate_handler.py
pythononwheels/start/generate_migration.py
pythononwheels/start/generate_model.py
pythononwheels/start/generate_observer.py
pythononwheels/start/generate_scaffold.py
pythononwheels/start/generate_view.py
pythononwheels/start/init_sqldb_environment.py
pythononwheels/start/requirements.txt
pythononwheels/start/server.py
pythononwheels/start/update_db.py
pythononwheels/start/conf/alembic.ini
pythononwheels/start/conf/config.py
pythononwheels/start/conf/update_conf.py
pythononwheels/start/data/readme.txt
pythononwheels/start/database/__init__.py
pythononwheels/start/database/elasticdblib.py
pythononwheels/start/database/mongodblib.py
pythononwheels/start/database/redisdblib.py
pythononwheels/start/database/sqldblib.py
pythononwheels/start/database/tinydblib.py
pythononwheels/start/handlers/__init__.py
pythononwheels/start/handlers/base.py
pythononwheels/start/handlers/hello_world.py
pythononwheels/start/handlers/powhandler.py
pythononwheels/start/handlers/powhandlermixin.py
pythononwheels/start/handlers/powwshandler.py
pythononwheels/start/handlers/shorties.py
pythononwheels/start/lib/application.py
pythononwheels/start/lib/decoders.py
pythononwheels/start/lib/encoders.py
pythononwheels/start/lib/powlib.py
pythononwheels/start/log/readme.txt
pythononwheels/start/migrations/env.py
pythononwheels/start/migrations/script.py.mako
pythononwheels/start/migrations/versions/README
pythononwheels/start/models/__init__.py
pythononwheels/start/models/modelobject.py
pythononwheels/start/models/elastic/__init__.py
pythononwheels/start/models/elastic/basemodel.py
pythononwheels/start/models/elastic/dsl_basemodel.py
pythononwheels/start/models/mongodb/__init__.py
pythononwheels/start/models/mongodb/basemodel.py
pythononwheels-0.925.54.dist-info/METADATA
pythononwheels-0.925.54.dist-info/WHEEL
pythononwheels-0.925.54.dist-info/entry_points.txt
pythononwheels-0.925.54.dist-info/top_level.txt
pythononwheels-0.925.54.dist-info/RECORD
