Metadata-Version: 2.1
Name: pythononwheels
Version: 0.925.54
Summary: The simple, quick and easy generative web framework for python
Home-page: http://www.pythononwheels.org
Author: khz
Author-email: khz@tzi.org
License: MIT
Keywords: framework web development
Classifier: Development Status :: 4 - Beta
Classifier: Environment :: Web Environment
Classifier: Intended Audience :: Developers
Classifier: License :: OSI Approved :: MIT License
Classifier: Programming Language :: Python :: 3 :: Only
Classifier: Topic :: Internet :: WWW/HTTP
Classifier: Topic :: Internet :: WWW/HTTP :: Dynamic Content
Classifier: Topic :: Software Development :: Libraries :: Application Frameworks
Classifier: Topic :: Software Development :: Libraries :: Python Modules 
Requires-Dist: tornado
